Metadata-Version: 1.0
Name: eda-simple
Version: 0.2
Summary: Simple exploratory data analysis
Home-page: UNKNOWN
Author: UNKNOWN
Author-email: UNKNOWN
License: UNKNOWN
Platform: UNKNOWN
